django_socialnetworks-0.5.0a7.dist-info/DESCRIPTION.rst
django_socialnetworks-0.5.0a7.dist-info/METADATA
django_socialnetworks-0.5.0a7.dist-info/RECORD
django_socialnetworks-0.5.0a7.dist-info/WHEEL
django_socialnetworks-0.5.0a7.dist-info/metadata.json
django_socialnetworks-0.5.0a7.dist-info/top_level.txt
socialnetworks/__init__.py
socialnetworks/models.py
socialnetworks/signals.py
socialnetworks/urls.py
socialnetworks/core/__init__.py
socialnetworks/core/backends.py
socialnetworks/core/clients.py
socialnetworks/core/defaults.py
socialnetworks/core/forms.py
socialnetworks/core/models.py
socialnetworks/core/settings.py
socialnetworks/core/utils.py
socialnetworks/core/views.py
socialnetworks/facebook/__init__.py
socialnetworks/facebook/backends.py
socialnetworks/facebook/clients.py
socialnetworks/facebook/models.py
socialnetworks/facebook/settings.py
socialnetworks/facebook/urls.py
socialnetworks/facebook/utils.py
socialnetworks/facebook/views.py
socialnetworks/facebook/migrations/0001_initial.py
socialnetworks/facebook/migrations/__init__.py
socialnetworks/facebook/south_migrations/0001_initial.py
socialnetworks/facebook/south_migrations/__init__.py
socialnetworks/facebook/templates/facebook/login_button.html
socialnetworks/facebook/templates/facebook/setup_form.html
socialnetworks/facebook/templates/facebook/share_button.html
socialnetworks/facebook/templatetags/__init__.py
socialnetworks/facebook/templatetags/facebook.py
socialnetworks/github/__init__.py
socialnetworks/github/backends.py
socialnetworks/github/clients.py
socialnetworks/github/decorators.py
socialnetworks/github/models.py
socialnetworks/github/settings.py
socialnetworks/github/urls.py
socialnetworks/github/utils.py
socialnetworks/github/views.py
socialnetworks/github/migrations/0001_initial.py
socialnetworks/github/migrations/__init__.py
socialnetworks/github/south_migrations/0001_initial.py
socialnetworks/github/south_migrations/__init__.py
socialnetworks/github/templates/github/login_button.html
socialnetworks/github/templates/github/setup_form.html
socialnetworks/github/templates/github/share_button.html
socialnetworks/github/templatetags/__init__.py
socialnetworks/github/templatetags/github.py
socialnetworks/gravatar/__init__.py
