Metadata-Version: 2.0
Name: django-socialnetworks
Version: 0.5.0a7
Summary: Extends Django with “log in” and “share” functionalities for the most common social networks.
Home-page: https://github.com/gGonz/django-socialnetworks
Author: Gabriel González
Author-email: zurg.cei@gmail.com
License: Apache License (2.0)
Platform: UNKNOWN
Classifier: Development Status :: 4 - Beta
Classifier: Intended Audience :: Developers
Classifier: License :: OSI Approved :: Apache Software License
Classifier: Environment :: Web Environment
Classifier: Operating System :: OS Independent
Classifier: Programming Language :: Python
Classifier: Framework :: Django
Classifier: Topic :: Software Development :: Libraries :: Python Modules
Classifier: Topic :: Internet
Requires-Dist: Django (>=1.5)
Requires-Dist: pytz
Requires-Dist: requests-oauthlib
Requires-Dist: unidecode
Provides-Extra: security
Requires-Dist: requests[security]; extra == 'security'
